koodaus/__init__.py
koodaus/integers.py
koodaus/py.typed
koodaus-0.2.dist-info/LICENSE
koodaus-0.2.dist-info/METADATA
koodaus-0.2.dist-info/WHEEL
koodaus-0.2.dist-info/top_level.txt
koodaus-0.2.dist-info/RECORD
