Metadata-Version: 2.1
Name: koodaus
Version: 0.2
Summary: Encoding/decoding library for Python
Home-page: https://github.com/valohai/koodaus
Author: Valohai
Author-email: info@valohai.com
License: MIT
Platform: UNKNOWN
Requires-Python: >=3.6
License-File: LICENSE
Provides-Extra: lint
Requires-Dist: flake8 ; extra == 'lint'
Requires-Dist: isort ; extra == 'lint'
Requires-Dist: mypy ; extra == 'lint'
Provides-Extra: test
Requires-Dist: pytest ; extra == 'test'
Requires-Dist: pytest-cov ; extra == 'test'
